django_mailman3-1.3.15.dist-info/METADATA
django_mailman3-1.3.15.dist-info/WHEEL
django_mailman3-1.3.15.dist-info/licenses/COPYING.txt
django_mailman3/__init__.py
django_mailman3/admin.py
django_mailman3/apps.py
django_mailman3/context_processors.py
django_mailman3/forms.py
django_mailman3/lib/__init__.py
django_mailman3/lib/auth/__init__.py
django_mailman3/lib/auth/fedora/__init__.py
django_mailman3/lib/auth/fedora/provider.py
django_mailman3/lib/auth/fedora/urls.py
django_mailman3/lib/auth/fedora/views.py
django_mailman3/lib/mailman.py
django_mailman3/lib/paginator.py
django_mailman3/lib/scrub.py
django_mailman3/lib/user.py
django_mailman3/locale/LINGUAS
django_mailman3/locale/af/LC_MESSAGES/django.po
django_mailman3/locale/ak/LC_MESSAGES/django.po
django_mailman3/locale/am/LC_MESSAGES/django.po
django_mailman3/locale/an/LC_MESSAGES/django.po
django_mailman3/locale/ar/LC_MESSAGES/django.po
django_mailman3/locale/ast/LC_MESSAGES/django.po
django_mailman3/locale/az/LC_MESSAGES/django.po
django_mailman3/locale/be/LC_MESSAGES/django.po
django_mailman3/locale/bem/LC_MESSAGES/django.po
django_mailman3/locale/bg/LC_MESSAGES/django.po
django_mailman3/locale/bn/LC_MESSAGES/django.po
django_mailman3/locale/bo/LC_MESSAGES/django.po
django_mailman3/locale/br/LC_MESSAGES/django.po
django_mailman3/locale/bs/LC_MESSAGES/django.po
django_mailman3/locale/ca/LC_MESSAGES/django.po
django_mailman3/locale/ca@valencia/LC_MESSAGES/django.po
django_mailman3/locale/ce/LC_MESSAGES/django.po
django_mailman3/locale/ckb/LC_MESSAGES/django.po
django_mailman3/locale/co/LC_MESSAGES/django.po
django_mailman3/locale/crh/LC_MESSAGES/django.po
django_mailman3/locale/cs/LC_MESSAGES/django.po
django_mailman3/locale/cv/LC_MESSAGES/django.po
django_mailman3/locale/cy/LC_MESSAGES/django.po
django_mailman3/locale/da/LC_MESSAGES/django.po
django_mailman3/locale/de/LC_MESSAGES/django.po
django_mailman3/locale/el/LC_MESSAGES/django.po
django_mailman3/locale/en_AU/LC_MESSAGES/django.po
django_mailman3/locale/en_CA/LC_MESSAGES/django.po
django_mailman3/locale/en_GB/LC_MESSAGES/django.po
django_mailman3/locale/eo/LC_MESSAGES/django.po
django_mailman3-1.3.15.dist-info/RECORD
