Metadata-Version: 2.1
Name: django-mailman3
Version: 1.3.15
Summary: Django library to help interaction with Mailman
Keywords: mailman django
Maintainer-Email: Mailman Developers <mailman-developers@python.org>
License: GPLv3
Classifier: Development Status :: 4 - Beta
Classifier: Framework :: Django
Classifier: License :: OSI Approved :: GNU General Public License v3 (GPLv3)
Classifier: Programming Language :: Python :: 3
Classifier: Topic :: Communications :: Email :: Mailing List Servers
Project-URL: Homepage, https://gitlab.com/mailman/django-mailman3
Requires-Python: >=3.9
Requires-Dist: django-allauth[openid,socialaccount]>=0.63
Requires-Dist: django-gravatar2>=1.0.6
Requires-Dist: django<5.1,>=4.2
Requires-Dist: mailmanclient>=3.3.3
